[
  { "lemma": "de", "pos": "preposition", "gloss": "of / from" },
  { "lemma": "la", "pos": "determiner", "gloss": "the (f.)" },
  { "lemma": "el", "pos": "determiner", "gloss": "the (m.)" },
  { "lemma": "que", "pos": "conjunction", "gloss": "that / which" },
  { "lemma": "y", "pos": "conjunction", "gloss": "and" },
  { "lemma": "a", "pos": "preposition", "gloss": "to / at" },
  { "lemma": "en", "pos": "preposition", "gloss": "in / on" },
  { "lemma": "un", "pos": "determiner", "gloss": "a / an (m.)" },
  { "lemma": "una", "pos": "determiner", "gloss": "a / an (f.)" },
  { "lemma": "ser", "pos": "verb", "gloss": "to be" },
  { "lemma": "se", "pos": "pronoun", "gloss": "oneself / itself" },
  { "lemma": "no", "pos": "adverb", "gloss": "no / not" },
  { "lemma": "haber", "pos": "verb", "gloss": "to have (auxiliary)" },
  { "lemma": "por", "pos": "preposition", "gloss": "for / by / through" },
  { "lemma": "con", "pos": "preposition", "gloss": "with" },
  { "lemma": "su", "pos": "determiner", "gloss": "his / her / their" },
  { "lemma": "para", "pos": "preposition", "gloss": "for / in order to" },
  { "lemma": "como", "pos": "conjunction", "gloss": "like / as" },
  { "lemma": "estar", "pos": "verb", "gloss": "to be (state/location)" },
  { "lemma": "tener", "pos": "verb", "gloss": "to have" },
  { "lemma": "le", "pos": "pronoun", "gloss": "to him / to her" },
  { "lemma": "lo", "pos": "pronoun", "gloss": "it / him" },
  { "lemma": "todo", "pos": "determiner", "gloss": "all / everything" },
  { "lemma": "pero", "pos": "conjunction", "gloss": "but" },
  { "lemma": "más", "pos": "adverb", "gloss": "more" },
  { "lemma": "hacer", "pos": "verb", "gloss": "to do / to make" },
  { "lemma": "o", "pos": "conjunction", "gloss": "or" },
  { "lemma": "poder", "pos": "verb", "gloss": "to be able / can" },
  { "lemma": "decir", "pos": "verb", "gloss": "to say / to tell" },
  { "lemma": "este", "pos": "determiner", "gloss": "this" },
  { "lemma": "ir", "pos": "verb", "gloss": "to go" },
  { "lemma": "otro", "pos": "determiner", "gloss": "other / another" },
  { "lemma": "ese", "pos": "determiner", "gloss": "that" },
  { "lemma": "si", "pos": "conjunction", "gloss": "if" },
  { "lemma": "me", "pos": "pronoun", "gloss": "me / to me" },
  { "lemma": "ya", "pos": "adverb", "gloss": "already / now" },
  { "lemma": "ver", "pos": "verb", "gloss": "to see" },
  { "lemma": "porque", "pos": "conjunction", "gloss": "because" },
  { "lemma": "dar", "pos": "verb", "gloss": "to give" },
  { "lemma": "cuando", "pos": "conjunction", "gloss": "when" },
  { "lemma": "muy", "pos": "adverb", "gloss": "very" },
  { "lemma": "sin", "pos": "preposition", "gloss": "without" },
  { "lemma": "sobre", "pos": "preposition", "gloss": "on / about" },
  { "lemma": "también", "pos": "adverb", "gloss": "also / too" },
  { "lemma": "hasta", "pos": "preposition", "gloss": "until / up to" },
  { "lemma": "donde", "pos": "adverb", "gloss": "where" },
  { "lemma": "quien", "pos": "pronoun", "gloss": "who" },
  { "lemma": "desde", "pos": "preposition", "gloss": "from / since" },
  { "lemma": "nosotros", "pos": "pronoun", "gloss": "we" },
  { "lemma": "durante", "pos": "preposition", "gloss": "during" },
  { "lemma": "uno", "pos": "numeral", "gloss": "one" },
  { "lemma": "ni", "pos": "conjunction", "gloss": "nor / neither" },
  { "lemma": "contra", "pos": "preposition", "gloss": "against" },
  { "lemma": "yo", "pos": "pronoun", "gloss": "I" },
  { "lemma": "tú", "pos": "pronoun", "gloss": "you" },
  { "lemma": "él", "pos": "pronoun", "gloss": "he" },
  { "lemma": "ella", "pos": "pronoun", "gloss": "she" },
  { "lemma": "qué", "pos": "pronoun", "gloss": "what" },
  { "lemma": "saber", "pos": "verb", "gloss": "to know" },
  { "lemma": "querer", "pos": "verb", "gloss": "to want / to love" },
  { "lemma": "llegar", "pos": "verb", "gloss": "to arrive" },
  { "lemma": "pasar", "pos": "verb", "gloss": "to pass / to happen" },
  { "lemma": "deber", "pos": "verb", "gloss": "must / to owe" },
  { "lemma": "poner", "pos": "verb", "gloss": "to put" },
  { "lemma": "parecer", "pos": "verb", "gloss": "to seem" },
  { "lemma": "quedar", "pos": "verb", "gloss": "to stay / to remain" },
  { "lemma": "creer", "pos": "verb", "gloss": "to believe" },
  { "lemma": "hablar", "pos": "verb", "gloss": "to speak" },
  { "lemma": "llevar", "pos": "verb", "gloss": "to carry / to take" },
  { "lemma": "dejar", "pos": "verb", "gloss": "to leave / to let" },
  { "lemma": "seguir", "pos": "verb", "gloss": "to follow / to continue" },
  { "lemma": "encontrar", "pos": "verb", "gloss": "to find" },
  { "lemma": "llamar", "pos": "verb", "gloss": "to call" },
  { "lemma": "venir", "pos": "verb", "gloss": "to come" },
  { "lemma": "pensar", "pos": "verb", "gloss": "to think" },
  { "lemma": "salir", "pos": "verb", "gloss": "to leave / to go out" },
  { "lemma": "volver", "pos": "verb", "gloss": "to return" },
  { "lemma": "comer", "pos": "verb", "gloss": "to eat" },
  { "lemma": "beber", "pos": "verb", "gloss": "to drink" },
  { "lemma": "vivir", "pos": "verb", "gloss": "to live" },
  { "lemma": "trabajar", "pos": "verb", "gloss": "to work" },
  { "lemma": "comprar", "pos": "verb", "gloss": "to buy" },
  { "lemma": "leer", "pos": "verb", "gloss": "to read" },
  { "lemma": "escribir", "pos": "verb", "gloss": "to write" },
  { "lemma": "abrir", "pos": "verb", "gloss": "to open" },
  { "lemma": "tiempo", "pos": "noun", "gloss": "time / weather" },
  { "lemma": "año", "pos": "noun", "gloss": "year" },
  { "lemma": "día", "pos": "noun", "gloss": "day" },
  { "lemma": "vez", "pos": "noun", "gloss": "time (occurrence)" },
  { "lemma": "hombre", "pos": "noun", "gloss": "man" },
  { "lemma": "mujer", "pos": "noun", "gloss": "woman" },
  { "lemma": "vida", "pos": "noun", "gloss": "life" },
  { "lemma": "mano", "pos": "noun", "gloss": "hand" },
  { "lemma": "parte", "pos": "noun", "gloss": "part" },
  { "lemma": "niño", "pos": "noun", "gloss": "boy / child" },
  { "lemma": "niña", "pos": "noun", "gloss": "girl" },
  { "lemma": "mundo", "pos": "noun", "gloss": "world" },
  { "lemma": "país", "pos": "noun", "gloss": "country" },
  { "lemma": "casa", "pos": "noun", "gloss": "house / home" },
  { "lemma": "agua", "pos": "noun", "gloss": "water" },
  { "lemma": "cosa", "pos": "noun", "gloss": "thing" },
  { "lemma": "momento", "pos": "noun", "gloss": "moment" },
  { "lemma": "trabajo", "pos": "noun", "gloss": "work / job" },
  { "lemma": "amigo", "pos": "noun", "gloss": "friend (m.)" },
  { "lemma": "amiga", "pos": "noun", "gloss": "friend (f.)" },
  { "lemma": "comida", "pos": "noun", "gloss": "food / meal" },
  { "lemma": "ciudad", "pos": "noun", "gloss": "city" },
  { "lemma": "libro", "pos": "noun", "gloss": "book" },
  { "lemma": "calle", "pos": "noun", "gloss": "street" },
  { "lemma": "noche", "pos": "noun", "gloss": "night" },
  { "lemma": "mañana", "pos": "noun", "gloss": "morning / tomorrow" },
  { "lemma": "semana", "pos": "noun", "gloss": "week" },
  { "lemma": "gente", "pos": "noun", "gloss": "people" },
  { "lemma": "dinero", "pos": "noun", "gloss": "money" },
  { "lemma": "escuela", "pos": "noun", "gloss": "school" },
  { "lemma": "familia", "pos": "noun", "gloss": "family" },
  { "lemma": "padre", "pos": "noun", "gloss": "father" },
  { "lemma": "madre", "pos": "noun", "gloss": "mother" },
  { "lemma": "perro", "pos": "noun", "gloss": "dog" },
  { "lemma": "gato", "pos": "noun", "gloss": "cat" },
  { "lemma": "mesa", "pos": "noun", "gloss": "table" },
  { "lemma": "puerta", "pos": "noun", "gloss": "door" },
  { "lemma": "pan", "pos": "noun", "gloss": "bread" },
  { "lemma": "leche", "pos": "noun", "gloss": "milk" },
  { "lemma": "café", "pos": "noun", "gloss": "coffee" },
  { "lemma": "manzana", "pos": "noun", "gloss": "apple" },
  { "lemma": "bueno", "pos": "adjective", "gloss": "good" },
  { "lemma": "malo", "pos": "adjective", "gloss": "bad" },
  { "lemma": "grande", "pos": "adjective", "gloss": "big / large" },
  { "lemma": "pequeño", "pos": "adjective", "gloss": "small" },
  { "lemma": "nuevo", "pos": "adjective", "gloss": "new" },
  { "lemma": "viejo", "pos": "adjective", "gloss": "old" },
  { "lemma": "mismo", "pos": "adjective", "gloss": "same" },
  { "lemma": "importante", "pos": "adjective", "gloss": "important" },
  { "lemma": "feliz", "pos": "adjective", "gloss": "happy" },
  { "lemma": "rojo", "pos": "adjective", "gloss": "red" },
  { "lemma": "alto", "pos": "adjective", "gloss": "tall / high" },
  { "lemma": "hola", "pos": "interjection", "gloss": "hello" },
  { "lemma": "gracias", "pos": "interjection", "gloss": "thank you" },
  { "lemma": "dos", "pos": "numeral", "gloss": "two" },
  { "lemma": "tres", "pos": "numeral", "gloss": "three" },
  { "lemma": "cuatro", "pos": "numeral", "gloss": "four" },
  { "lemma": "cinco", "pos": "numeral", "gloss": "five" },
  { "lemma": "seis", "pos": "numeral", "gloss": "six" },
  { "lemma": "siete", "pos": "numeral", "gloss": "seven" },
  { "lemma": "ocho", "pos": "numeral", "gloss": "eight" },
  { "lemma": "nueve", "pos": "numeral", "gloss": "nine" },
  { "lemma": "diez", "pos": "numeral", "gloss": "ten" },
  { "lemma": "color", "pos": "noun", "gloss": "color" },
  { "lemma": "azul", "pos": "adjective", "gloss": "blue" },
  { "lemma": "verde", "pos": "adjective", "gloss": "green" },
  { "lemma": "negro", "pos": "adjective", "gloss": "black" },
  { "lemma": "blanco", "pos": "adjective", "gloss": "white" },
  { "lemma": "amarillo", "pos": "adjective", "gloss": "yellow" },
  { "lemma": "hoy", "pos": "adverb", "gloss": "today" },
  { "lemma": "ayer", "pos": "adverb", "gloss": "yesterday" },
  { "lemma": "ahora", "pos": "adverb", "gloss": "now" },
  { "lemma": "hora", "pos": "noun", "gloss": "hour" },
  { "lemma": "minuto", "pos": "noun", "gloss": "minute" },
  { "lemma": "tarde", "pos": "noun", "gloss": "afternoon" },
  { "lemma": "temprano", "pos": "adverb", "gloss": "early" },
  { "lemma": "fruta", "pos": "noun", "gloss": "fruit" },
  { "lemma": "verdura", "pos": "noun", "gloss": "vegetable" },
  { "lemma": "carne", "pos": "noun", "gloss": "meat" },
  { "lemma": "pescado", "pos": "noun", "gloss": "fish (food)" },
  { "lemma": "queso", "pos": "noun", "gloss": "cheese" },
  { "lemma": "huevo", "pos": "noun", "gloss": "egg" },
  { "lemma": "arroz", "pos": "noun", "gloss": "rice" },
  { "lemma": "sopa", "pos": "noun", "gloss": "soup" },
  { "lemma": "vino", "pos": "noun", "gloss": "wine" },
  { "lemma": "jugo", "pos": "noun", "gloss": "juice" },
  { "lemma": "azúcar", "pos": "noun", "gloss": "sugar" },
  { "lemma": "sal", "pos": "noun", "gloss": "salt" },
  { "lemma": "aeropuerto", "pos": "noun", "gloss": "airport" },
  { "lemma": "hotel", "pos": "noun", "gloss": "hotel" },
  { "lemma": "restaurante", "pos": "noun", "gloss": "restaurant" },
  { "lemma": "tienda", "pos": "noun", "gloss": "shop / store" },
  { "lemma": "mercado", "pos": "noun", "gloss": "market" },
  { "lemma": "banco", "pos": "noun", "gloss": "bank" },
  { "lemma": "hospital", "pos": "noun", "gloss": "hospital" },
  { "lemma": "baño", "pos": "noun", "gloss": "bathroom" },
  { "lemma": "parque", "pos": "noun", "gloss": "park" },
  { "lemma": "cabeza", "pos": "noun", "gloss": "head" },
  { "lemma": "ojo", "pos": "noun", "gloss": "eye" },
  { "lemma": "boca", "pos": "noun", "gloss": "mouth" },
  { "lemma": "pie", "pos": "noun", "gloss": "foot" },
  { "lemma": "brazo", "pos": "noun", "gloss": "arm" },
  { "lemma": "pierna", "pos": "noun", "gloss": "leg" },
  { "lemma": "corazón", "pos": "noun", "gloss": "heart" },
  { "lemma": "necesitar", "pos": "verb", "gloss": "to need" },
  { "lemma": "usar", "pos": "verb", "gloss": "to use" },
  { "lemma": "ayudar", "pos": "verb", "gloss": "to help" },
  { "lemma": "buscar", "pos": "verb", "gloss": "to look for" },
  { "lemma": "esperar", "pos": "verb", "gloss": "to wait / to hope" },
  { "lemma": "vender", "pos": "verb", "gloss": "to sell" },
  { "lemma": "aprender", "pos": "verb", "gloss": "to learn" },
  { "lemma": "entender", "pos": "verb", "gloss": "to understand" },
  { "lemma": "recibir", "pos": "verb", "gloss": "to receive" },
  { "lemma": "preguntar", "pos": "verb", "gloss": "to ask" },
  { "lemma": "pagar", "pos": "verb", "gloss": "to pay" },
  { "lemma": "viajar", "pos": "verb", "gloss": "to travel" },
  { "lemma": "triste", "pos": "adjective", "gloss": "sad" },
  { "lemma": "cansado", "pos": "adjective", "gloss": "tired" },
  { "lemma": "enfermo", "pos": "adjective", "gloss": "sick" },
  { "lemma": "fácil", "pos": "adjective", "gloss": "easy" },
  { "lemma": "difícil", "pos": "adjective", "gloss": "difficult" },
  { "lemma": "caro", "pos": "adjective", "gloss": "expensive" },
  { "lemma": "barato", "pos": "adjective", "gloss": "cheap" },
  { "lemma": "bonito", "pos": "adjective", "gloss": "pretty" },
  { "lemma": "fuerte", "pos": "adjective", "gloss": "strong" },
  { "lemma": "débil", "pos": "adjective", "gloss": "weak" }
]
